c7n_oci/constants.py
c7n_oci/entry.py
c7n_oci/log.py
c7n_oci/output.py
c7n_oci/provider.py
c7n_oci/query.py
c7n_oci/session.py
c7n_oci/utils.py
c7n_oci/actions/__init__.py
c7n_oci/actions/base.py
c7n_oci/filters/__init__.py
c7n_oci/resources/__init__.py
c7n_oci/resources/compute.py
c7n_oci/resources/dns.py
c7n_oci/resources/identity.py
c7n_oci/resources/object_storage.py
c7n_oci/resources/resource_map.py
c7n_oci/resources/virtual_network.py
c7n_oci-0.1.23.dist-info/METADATA
c7n_oci-0.1.23.dist-info/WHEEL
c7n_oci-0.1.23.dist-info/RECORD
